mlflow_oss/artifact_repo.py
mlflow_oss_store-0.1.1.dist-info/entry_points.txt
mlflow_oss_store-0.1.1.dist-info/WHEEL
mlflow_oss_store-0.1.1.dist-info/METADATA
mlflow_oss_store-0.1.1.dist-info/RECORD
